{
  "data": [
    {
      "id": "03036d75-1a9a-4625-b9b1-dc1addb095ad",
      "type": "order",
      "status": "complete",
      "payment": "paid",
      "customer": {
        "name": "Customer 1",
        "email": "customer1@example.com"
      },
      "relationships": {
        "items": {
          "data": [
            {
              "type": "item",
              "id": "e8c4c695-810c-4021-87e2-53c0f2442cd9",
              "name": "Red Hat",
              "sku": "PcmProdSku2_837138451048"
            },
            {
              "type": "item",
              "id": "d35e9601-4ae9-4de6-a141-8538b5a58ee9",
              "name": "Orange Gloves",
              "sku": "PcmProdSku7_837138451083"
            },
            {
              "type": "item",
              "id": "8332beb6-a1ef-4494-844f-d42942817117",
              "name": "Yellow Shirt",
              "sku": "PcmProdSku4_837138451062"
            }
          ]
        }
      }
    },
    {
      "id": "5199b98c-2f04-4ac7-a0bb-de0518c50d0c",
      "type": "order",
      "status": "complete",
      "payment": "paid",
      "customer": {
        "name": "Customer 2",
        "email": "customer2@example.com"
      },
      "relationships": {
        "items": {
          "data": [
            {
              "type": "item",
              "id": "ffe0d3c5-bf8f-4e44-9f76-4e55c1324025",
              "name": "White Socks",
              "sku": "PIMBundle-sku-122527558739"
            },
            {
              "type": "item",
              "id": "31fd148f-b2a3-40b7-8815-02c4aeea2e80",
              "name": "Yellow Shirt",
              "sku": "PcmProdSku4_837138451062"
            },
            {
              "type": "item",
              "id": "8c35817d-faa1-433a-ba59-fc446ad64ced",
              "name": "Green Shoe",
              "sku": "PcmProdSku1_820633028024"
            }
          ]
        }
      }
    },
    {
      "id": "0613282d-b0cd-4b55-980b-c6e8bf37be30",
      "type": "order",
      "status": "complete",
      "payment": "paid",
      "customer": {
        "name": "Customer 3",
        "email": "customer3@example.com"
      },
      "relationships": {
        "items": {
          "data": [
            {
              "type": "item",
              "id": "57a8f6f2-2ea1-4a66-9173-d366d4ccc035",
              "name": "Purple Scarf",
              "sku": "PcmProdSku6_837138451076"
            },
            {
              "type": "item",
              "id": "1e8bfc82-1dd1-4b51-870d-89c6b8c9f5d7",
              "name": "Brown Boots",
              "sku": "PcmProdSku9_837138451097"
            },
            {
              "type": "item",
              "id": "6632a176-c5da-4828-b73e-db386b4202fd",
              "name": "Blue Jeans",
              "sku": "PcmProdSku3_837138451055"
            }
          ]
        }
      }
    },
    {
      "id": "a8420103-4a6f-46bb-8dd3-9780e1098a60",
      "type": "order",
      "status": "complete",
      "payment": "paid",
      "customer": {
        "name": "Customer 4",
        "email": "customer4@example.com"
      },
      "relationships": {
        "items": {
          "data": [
            {
              "type": "item",
              "id": "b0aec017-b8a7-4862-9d9b-53d1d2b28400",
              "name": "Blue Jeans",
              "sku": "PcmProdSku3_837138451055"
            },
            {
              "type": "item",
              "id": "e214513b-2c2a-4db5-a4c9-6294272db62a",
              "name": "Pink Hat",
              "sku": "PcmProdSku8_837138451090"
            },
            {
              "type": "item",
              "id": "630827e1-67b3-4215-bede-e2d5bfcb63fc",
              "name": "Red Hat",
              "sku": "PcmProdSku2_837138451048"
            }
          ]
        }
      }
    },
    {
      "id": "0036ba8a-108a-4be8-85b8-2ec49af0553b",
      "type": "order",
      "status": "complete",
      "payment": "paid",
      "customer": {
        "name": "Customer 5",
        "email": "customer5@example.com"
      },
      "relationships": {
        "items": {
          "data": [
            {
              "type": "item",
              "id": "560d289f-477e-4a14-bc5a-527a2dd2b5bd",
              "name": "Pink Hat",
              "sku": "PcmProdSku8_837138451090"
            },
            {
              "type": "item",
              "id": "776454f4-b052-4257-8209-f636b960886b",
              "name": "Black Belt",
              "sku": "PcmProdSku5_837138451069"
            }
          ]
        }
      }
    },
    {
      "id": "c6f9f041-9dd7-49b6-a280-768a4effdad3",
      "type": "order",
      "status": "complete",
      "payment": "paid",
      "customer": {
        "name": "Customer 6",
        "email": "customer6@example.com"
      },
      "relationships": {
        "items": {
          "data": [
            {
              "type": "item",
              "id": "12659fd3-ecd0-4dc5-9aec-62d44192739e",
              "name": "Purple Scarf",
              "sku": "PcmProdSku6_837138451076"
            },
            {
              "type": "item",
              "id": "639620b4-8919-4d73-aa0d-42c89da4e378",
              "name": "Green Shoe",
              "sku": "PcmProdSku1_820633028024"
            }
          ]
        }
      }
    },
    {
      "id": "2040c361-fadc-4237-a330-45b61b3d2446",
      "type": "order",
      "status": "complete",
      "payment": "paid",
      "customer": {
        "name": "Customer 7",
        "email": "customer7@example.com"
      },
      "relationships": {
        "items": {
          "data": [
            {
              "type": "item",
              "id": "d329d54a-c56a-451d-ab7b-e376aeca96ed",
              "name": "Orange Gloves",
              "sku": "PcmProdSku7_837138451083"
            },
            {
              "type": "item",
              "id": "07842684-2fd9-4774-a0bc-b343ad4d97bc",
              "name": "Yellow Shirt",
              "sku": "PcmProdSku4_837138451062"
            },
            {
              "type": "item",
              "id": "aef7861a-316f-4e0b-afe7-70a2874c7449",
              "name": "Green Shoe",
              "sku": "PcmProdSku1_820633028024"
            }
          ]
        }
      }
    },
    {
      "id": "b2d8a3ed-e253-4595-97b5-28c90806ffc9",
      "type": "order",
      "status": "complete",
      "payment": "paid",
      "customer": {
        "name": "Customer 8",
        "email": "customer8@example.com"
      },
      "relationships": {
        "items": {
          "data": [
            {
              "type": "item",
              "id": "9bcde0b2-738f-4481-9271-0b82535da1a1",
              "name": "Orange Gloves",
              "sku": "PcmProdSku7_837138451083"
            },
            {
              "type": "item",
              "id": "68b4e257-84c0-47b3-be6c-68d2a61b1990",
              "name": "White Socks",
              "sku": "PIMBundle-sku-122527558739"
            },
            {
              "type": "item",
              "id": "dbcb1bc4-b34a-4044-bc66-65dddabeb2fb",
              "name": "Green Shoe",
              "sku": "PcmProdSku1_820633028024"
            }
          ]
        }
      }
    },
    {
      "id": "774a708d-e7ff-4c5b-a1f0-e4591ac1e92c",
      "type": "order",
      "status": "complete",
      "payment": "paid",
      "customer": {
        "name": "Customer 9",
        "email": "customer9@example.com"
      },
      "relationships": {
        "items": {
          "data": [
            {
              "type": "item",
              "id": "94bd7bcf-e137-4685-b2f2-aaa3748e02ca",
              "name": "Black Belt",
              "sku": "PcmProdSku5_837138451069"
            },
            {
              "type": "item",
              "id": "860a1047-0c84-4078-b433-35be68fb77cb",
              "name": "White Socks",
              "sku": "PIMBundle-sku-122527558739"
            },
            {
              "type": "item",
              "id": "8dd2a998-e5e2-4bb5-9b86-ecac2b1a2fe0",
              "name": "Brown Boots",
              "sku": "PcmProdSku9_837138451097"
            },
            {
              "type": "item",
              "id": "e703b276-361c-432d-b5aa-beddb599d695",
              "name": "Orange Gloves",
              "sku": "PcmProdSku7_837138451083"
            }
          ]
        }
      }
    },
    {
      "id": "80fb1ba4-2991-492a-866f-51da02586f0d",
      "type": "order",
      "status": "complete",
      "payment": "paid",
      "customer": {
        "name": "Customer 10",
        "email": "customer10@example.com"
      },
      "relationships": {
        "items": {
          "data": [
            {
              "type": "item",
              "id": "49e46741-1bc1-4c96-9415-23ec02d2a098",
              "name": "Pink Hat",
              "sku": "PcmProdSku8_837138451090"
            },
            {
              "type": "item",
              "id": "6143fd1d-8fec-4af4-9bae-a8a2d2953a7f",
              "name": "Brown Boots",
              "sku": "PcmProdSku9_837138451097"
            }
          ]
        }
      }
    },
    {
      "id": "6ab59e6d-e3a1-43ae-83ec-73fa52185da5",
      "type": "order",
      "status": "complete",
      "payment": "paid",
      "customer": {
        "name": "Customer 11",
        "email": "customer11@example.com"
      },
      "relationships": {
        "items": {
          "data": [
            {
              "type": "item",
              "id": "6edf0022-3b55-40ad-b777-039f58fd40c7",
              "name": "Blue Jeans",
              "sku": "PcmProdSku3_837138451055"
            },
            {
              "type": "item",
              "id": "e455f93c-8fe8-4de4-813d-e2bd900b090d",
              "name": "Black Belt",
              "sku": "PcmProdSku5_837138451069"
            },
            {
              "type": "item",
              "id": "1f345a2a-0b5f-443b-b2c0-b4ce3eeaeac5",
              "name": "Brown Boots",
              "sku": "PcmProdSku9_837138451097"
            }
          ]
        }
      }
    },
    {
      "id": "cc8d4944-3d15-45a2-b057-9358eb8435f0",
      "type": "order",
      "status": "complete",
      "payment": "paid",
      "customer": {
        "name": "Customer 12",
        "email": "customer12@example.com"
      },
      "relationships": {
        "items": {
          "data": [
            {
              "type": "item",
              "id": "3c91aac0-7c0a-42b4-a8f8-9ba216fa1bd6",
              "name": "Purple Scarf",
              "sku": "PcmProdSku6_837138451076"
            },
            {
              "type": "item",
              "id": "b2fc997b-4fb8-4529-9a1a-5ceb9c3ca3ce",
              "name": "Yellow Shirt",
              "sku": "PcmProdSku4_837138451062"
            },
            {
              "type": "item",
              "id": "669d4894-db98-4fdd-af57-724a451a0965",
              "name": "Orange Gloves",
              "sku": "PcmProdSku7_837138451083"
            }
          ]
        }
      }
    },
    {
      "id": "7457a8a2-2785-47c4-9f4d-44d59f67d591",
      "type": "order",
      "status": "complete",
      "payment": "paid",
      "customer": {
        "name": "Customer 13",
        "email": "customer13@example.com"
      },
      "relationships": {
        "items": {
          "data": [
            {
              "type": "item",
              "id": "d816dabf-fd52-46a9-930c-cda5d98c1c0f",
              "name": "Black Belt",
              "sku": "PcmProdSku5_837138451069"
            },
            {
              "type": "item",
              "id": "2584e65a-e514-4a08-aec9-cc6bbc640c00",
              "name": "Purple Scarf",
              "sku": "PcmProdSku6_837138451076"
            },
            {
              "type": "item",
              "id": "cb02f2ca-c414-4647-9741-58bf69704aed",
              "name": "Blue Jeans",
              "sku": "PcmProdSku3_837138451055"
            },
            {
              "type": "item",
              "id": "e3e6e29a-677b-4900-bfff-99fc35cc5fbf",
              "name": "White Socks",
              "sku": "PIMBundle-sku-122527558739"
            }
          ]
        }
      }
    },
    {
      "id": "da3e5838-c70d-4d42-bc9b-8caeb3d79298",
      "type": "order",
      "status": "complete",
      "payment": "paid",
      "customer": {
        "name": "Customer 14",
        "email": "customer14@example.com"
      },
      "relationships": {
        "items": {
          "data": [
            {
              "type": "item",
              "id": "88e8a547-9ad1-45e4-b8b5-01c53eb44b6e",
              "name": "Purple Scarf",
              "sku": "PcmProdSku6_837138451076"
            },
            {
              "type": "item",
              "id": "bcd43295-b5a5-4626-b1f3-d4825c194b4a",
              "name": "Blue Jeans",
              "sku": "PcmProdSku3_837138451055"
            }
          ]
        }
      }
    },
    {
      "id": "6a745eae-e6ff-4cda-8966-43b52d76f298",
      "type": "order",
      "status": "complete",
      "payment": "paid",
      "customer": {
        "name": "Customer 15",
        "email": "customer15@example.com"
      },
      "relationships": {
        "items": {
          "data": [
            {
              "type": "item",
              "id": "c6ec2dc0-31f2-47e8-8e98-a2708d568582",
              "name": "White Socks",
              "sku": "PIMBundle-sku-122527558739"
            },
            {
              "type": "item",
              "id": "25cfa3ec-521d-44d0-b74a-bc7b2d803575",
              "name": "Purple Scarf",
              "sku": "PcmProdSku6_837138451076"
            }
          ]
        }
      }
    },
    {
      "id": "38160b66-0dcf-446f-9767-f4801049ee70",
      "type": "order",
      "status": "complete",
      "payment": "paid",
      "customer": {
        "name": "Customer 16",
        "email": "customer16@example.com"
      },
      "relationships": {
        "items": {
          "data": [
            {
              "type": "item",
              "id": "9d8cc92a-6da5-4ec3-98d1-658601ac0cbe",
              "name": "Red Hat",
              "sku": "PcmProdSku2_837138451048"
            },
            {
              "type": "item",
              "id": "75192cde-e048-43c5-99cb-32f4d5599bf9",
              "name": "Purple Scarf",
              "sku": "PcmProdSku6_837138451076"
            }
          ]
        }
      }
    },
    {
      "id": "07c9eb34-846f-4c90-a068-7a6763a83e06",
      "type": "order",
      "status": "complete",
      "payment": "paid",
      "customer": {
        "name": "Customer 17",
        "email": "customer17@example.com"
      },
      "relationships": {
        "items": {
          "data": [
            {
              "type": "item",
              "id": "6cd5a442-fe3f-490a-b791-3ea6f5aa0771",
              "name": "Green Shoe",
              "sku": "PcmProdSku1_820633028024"
            },
            {
              "type": "item",
              "id": "c2047225-c500-4dcf-97cb-f172c5fdb81b",
              "name": "Orange Gloves",
              "sku": "PcmProdSku7_837138451083"
            }
          ]
        }
      }
    },
    {
      "id": "3ef5f51a-89f4-459b-8e29-5fb33a9a90ca",
      "type": "order",
      "status": "complete",
      "payment": "paid",
      "customer": {
        "name": "Customer 18",
        "email": "customer18@example.com"
      },
      "relationships": {
        "items": {
          "data": [
            {
              "type": "item",
              "id": "03130bd7-b724-4b49-bc40-97b7bb2c4872",
              "name": "Green Shoe",
              "sku": "PcmProdSku1_820633028024"
            },
            {
              "type": "item",
              "id": "68e86484-80b3-48b3-b425-328e9738291e",
              "name": "Orange Gloves",
              "sku": "PcmProdSku7_837138451083"
            },
            {
              "type": "item",
              "id": "cff8158f-e648-44ce-9c47-1414f214d418",
              "name": "Yellow Shirt",
              "sku": "PcmProdSku4_837138451062"
            }
          ]
        }
      }
    },
    {
      "id": "3c76bdf9-f45a-40b0-af84-99814a2f1b38",
      "type": "order",
      "status": "complete",
      "payment": "paid",
      "customer": {
        "name": "Customer 19",
        "email": "customer19@example.com"
      },
      "relationships": {
        "items": {
          "data": [
            {
              "type": "item",
              "id": "6ce3f031-ed12-4d14-8c80-fdca17da81a1",
              "name": "White Socks",
              "sku": "PIMBundle-sku-122527558739"
            },
            {
              "type": "item",
              "id": "b94c04ed-2bf6-4ce8-86f8-fd45e065c977",
              "name": "Pink Hat",
              "sku": "PcmProdSku8_837138451090"
            }
          ]
        }
      }
    },
    {
      "id": "e216e294-87b1-454b-82d5-e91c4fc30d9a",
      "type": "order",
      "status": "complete",
      "payment": "paid",
      "customer": {
        "name": "Customer 20",
        "email": "customer20@example.com"
      },
      "relationships": {
        "items": {
          "data": [
            {
              "type": "item",
              "id": "a1a18aed-a237-4567-88a0-b54edf16e032",
              "name": "Yellow Shirt",
              "sku": "PcmProdSku4_837138451062"
            },
            {
              "type": "item",
              "id": "acdb142c-ba5e-4a32-93d3-9a3944ca083d",
              "name": "Pink Hat",
              "sku": "PcmProdSku8_837138451090"
            },
            {
              "type": "item",
              "id": "bdc01b1e-9cba-428f-aac6-af2928ba6514",
              "name": "White Socks",
              "sku": "PIMBundle-sku-122527558739"
            }
          ]
        }
      }
    },
    {
      "id": "e1a1e91e-5ba3-4f77-a9e2-c35b29654ef2",
      "type": "order",
      "status": "complete",
      "payment": "paid",
      "customer": {
        "name": "Customer 21",
        "email": "customer21@example.com"
      },
      "relationships": {
        "items": {
          "data": [
            {
              "type": "item",
              "id": "9a0ae3bf-dd8a-43d0-970b-5810c45a3562",
              "name": "Green Shoe",
              "sku": "PcmProdSku1_820633028024"
            },
            {
              "type": "item",
              "id": "a82cd315-14ce-4d69-bd33-308b21b03dca",
              "name": "Yellow Shirt",
              "sku": "PcmProdSku4_837138451062"
            },
            {
              "type": "item",
              "id": "819b46f1-82dd-40f6-829c-8ffb35c2b293",
              "name": "White Socks",
              "sku": "PIMBundle-sku-122527558739"
            },
            {
              "type": "item",
              "id": "693058f7-8785-4b12-9781-f4f8c0778a90",
              "name": "Blue Jeans",
              "sku": "PcmProdSku3_837138451055"
            }
          ]
        }
      }
    },
    {
      "id": "a82ef423-f878-477e-91d8-d01e277e08d4",
      "type": "order",
      "status": "complete",
      "payment": "paid",
      "customer": {
        "name": "Customer 22",
        "email": "customer22@example.com"
      },
      "relationships": {
        "items": {
          "data": [
            {
              "type": "item",
              "id": "530ceba9-c124-404d-b7a6-c416caea5c44",
              "name": "Pink Hat",
              "sku": "PcmProdSku8_837138451090"
            },
            {
              "type": "item",
              "id": "547fe755-57c1-402f-a6f8-b8c98e5acba6",
              "name": "Black Belt",
              "sku": "PcmProdSku5_837138451069"
            }
          ]
        }
      }
    },
    {
      "id": "528ebd4b-8712-4cca-ba9d-4838e30e2fda",
      "type": "order",
      "status": "complete",
      "payment": "paid",
      "customer": {
        "name": "Customer 23",
        "email": "customer23@example.com"
      },
      "relationships": {
        "items": {
          "data": [
            {
              "type": "item",
              "id": "b40c00dc-15bb-4705-99b6-5a96e4f8d338",
              "name": "Orange Gloves",
              "sku": "PcmProdSku7_837138451083"
            },
            {
              "type": "item",
              "id": "42cf6c95-0064-420c-97ed-57b3a6b5ceeb",
              "name": "Black Belt",
              "sku": "PcmProdSku5_837138451069"
            }
          ]
        }
      }
    },
    {
      "id": "5c6c709c-2adc-4fc8-ae3b-36c3bc748340",
      "type": "order",
      "status": "complete",
      "payment": "paid",
      "customer": {
        "name": "Customer 24",
        "email": "customer24@example.com"
      },
      "relationships": {
        "items": {
          "data": [
            {
              "type": "item",
              "id": "48ee70d7-6708-4904-9298-b928978a1efe",
              "name": "Purple Scarf",
              "sku": "PcmProdSku6_837138451076"
            },
            {
              "type": "item",
              "id": "73143460-39d2-4c86-9743-7a9fb4ec43b2",
              "name": "Blue Jeans",
              "sku": "PcmProdSku3_837138451055"
            }
          ]
        }
      }
    },
    {
      "id": "cc90d0ba-6de1-4020-8a2c-2ee5003365a1",
      "type": "order",
      "status": "complete",
      "payment": "paid",
      "customer": {
        "name": "Customer 25",
        "email": "customer25@example.com"
      },
      "relationships": {
        "items": {
          "data": [
            {
              "type": "item",
              "id": "961561c8-e8d5-46dc-8196-6176266a2be0",
              "name": "Red Hat",
              "sku": "PcmProdSku2_837138451048"
            },
            {
              "type": "item",
              "id": "ce9b4cdc-928e-4fa5-bd54-09ebf7278b88",
              "name": "Black Belt",
              "sku": "PcmProdSku5_837138451069"
            }
          ]
        }
      }
    },
    {
      "id": "4101f683-7e9c-42c1-a1fb-dcf8e82f7eaf",
      "type": "order",
      "status": "complete",
      "payment": "paid",
      "customer": {
        "name": "Customer 26",
        "email": "customer26@example.com"
      },
      "relationships": {
        "items": {
          "data": [
            {
              "type": "item",
              "id": "cd7e7509-b61c-45a9-a351-dd1147dee097",
              "name": "White Socks",
              "sku": "PIMBundle-sku-122527558739"
            },
            {
              "type": "item",
              "id": "5af263fd-5ed7-46f2-9b23-e1110c657b05",
              "name": "Pink Hat",
              "sku": "PcmProdSku8_837138451090"
            }
          ]
        }
      }
    },
    {
      "id": "6d8fc1c8-aef0-4b54-86fb-f1038e418fe8",
      "type": "order",
      "status": "complete",
      "payment": "paid",
      "customer": {
        "name": "Customer 27",
        "email": "customer27@example.com"
      },
      "relationships": {
        "items": {
          "data": [
            {
              "type": "item",
              "id": "f6c14c03-9867-47b5-a089-1fc2173a5235",
              "name": "Brown Boots",
              "sku": "PcmProdSku9_837138451097"
            },
            {
              "type": "item",
              "id": "7b413883-9e58-40b9-abf5-b125e9e156c2",
              "name": "White Socks",
              "sku": "PIMBundle-sku-122527558739"
            }
          ]
        }
      }
    },
    {
      "id": "99ed52ad-a110-4bf0-baca-6b02515cdfd3",
      "type": "order",
      "status": "complete",
      "payment": "paid",
      "customer": {
        "name": "Customer 28",
        "email": "customer28@example.com"
      },
      "relationships": {
        "items": {
          "data": [
            {
              "type": "item",
              "id": "54e53625-05fc-49ce-8054-5896711f4f52",
              "name": "Orange Gloves",
              "sku": "PcmProdSku7_837138451083"
            },
            {
              "type": "item",
              "id": "4b16c302-387b-4ea5-bd5d-7aef8c1a5f70",
              "name": "Yellow Shirt",
              "sku": "PcmProdSku4_837138451062"
            },
            {
              "type": "item",
              "id": "3fe7d79a-cd23-4769-857f-97719bb33953",
              "name": "Purple Scarf",
              "sku": "PcmProdSku6_837138451076"
            },
            {
              "type": "item",
              "id": "56050bb3-a1f6-4a07-9378-dee82da189e0",
              "name": "Blue Jeans",
              "sku": "PcmProdSku3_837138451055"
            }
          ]
        }
      }
    },
    {
      "id": "5e1e57e2-4fbd-4e8e-b7c2-7121dc5d86f0",
      "type": "order",
      "status": "complete",
      "payment": "paid",
      "customer": {
        "name": "Customer 29",
        "email": "customer29@example.com"
      },
      "relationships": {
        "items": {
          "data": [
            {
              "type": "item",
              "id": "60a7a4eb-e45f-4791-9670-2dc5afeb8d04",
              "name": "Purple Scarf",
              "sku": "PcmProdSku6_837138451076"
            },
            {
              "type": "item",
              "id": "c8bc3d40-4e51-48d9-b466-6bc670448890",
              "name": "Red Hat",
              "sku": "PcmProdSku2_837138451048"
            },
            {
              "type": "item",
              "id": "95e58424-8797-48c7-aee4-76caec66996d",
              "name": "Blue Jeans",
              "sku": "PcmProdSku3_837138451055"
            }
          ]
        }
      }
    },
    {
      "id": "5503e5ae-603e-4201-aa5e-62afb687f1db",
      "type": "order",
      "status": "complete",
      "payment": "paid",
      "customer": {
        "name": "Customer 30",
        "email": "customer30@example.com"
      },
      "relationships": {
        "items": {
          "data": [
            {
              "type": "item",
              "id": "0fc1a175-09bf-49fd-9769-aeacaf708a32",
              "name": "Orange Gloves",
              "sku": "PcmProdSku7_837138451083"
            },
            {
              "type": "item",
              "id": "acbfd1c4-53a8-405f-94b0-f6cbbad60610",
              "name": "Pink Hat",
              "sku": "PcmProdSku8_837138451090"
            }
          ]
        }
      }
    },
    {
      "id": "907b15e2-675b-4264-8524-3dc131f1783c",
      "type": "order",
      "status": "complete",
      "payment": "paid",
      "customer": {
        "name": "Customer 31",
        "email": "customer31@example.com"
      },
      "relationships": {
        "items": {
          "data": [
            {
              "type": "item",
              "id": "0a97c09e-05aa-4d67-bb62-c8d278c7bb9d",
              "name": "Red Hat",
              "sku": "PcmProdSku2_837138451048"
            },
            {
              "type": "item",
              "id": "6a01dc32-6d9b-42a1-a85a-c122cd3834de",
              "name": "Black Belt",
              "sku": "PcmProdSku5_837138451069"
            },
            {
              "type": "item",
              "id": "837f5605-a9cc-4bb9-968e-3a0b928b9732",
              "name": "Purple Scarf",
              "sku": "PcmProdSku6_837138451076"
            },
            {
              "type": "item",
              "id": "5b7c1b26-42ea-4922-95e7-ad7177ac885a",
              "name": "Pink Hat",
              "sku": "PcmProdSku8_837138451090"
            }
          ]
        }
      }
    },
    {
      "id": "90ee1997-521f-4c7c-98e0-015199787621",
      "type": "order",
      "status": "complete",
      "payment": "paid",
      "customer": {
        "name": "Customer 32",
        "email": "customer32@example.com"
      },
      "relationships": {
        "items": {
          "data": [
            {
              "type": "item",
              "id": "4f2e0265-d636-42a7-a086-ce47ad62e6e6",
              "name": "Brown Boots",
              "sku": "PcmProdSku9_837138451097"
            },
            {
              "type": "item",
              "id": "848e0a92-4797-45fb-bb80-2cfbca936d30",
              "name": "Black Belt",
              "sku": "PcmProdSku5_837138451069"
            },
            {
              "type": "item",
              "id": "6c6ab3fb-2099-4787-92c0-8d767b399b69",
              "name": "Purple Scarf",
              "sku": "PcmProdSku6_837138451076"
            },
            {
              "type": "item",
              "id": "a1f43a41-e21e-466b-b68b-17102e656e61",
              "name": "White Socks",
              "sku": "PIMBundle-sku-122527558739"
            }
          ]
        }
      }
    },
    {
      "id": "ed093a1b-a0ba-4917-9e68-686f7aa4faaf",
      "type": "order",
      "status": "complete",
      "payment": "paid",
      "customer": {
        "name": "Customer 33",
        "email": "customer33@example.com"
      },
      "relationships": {
        "items": {
          "data": [
            {
              "type": "item",
              "id": "460c55c5-3989-4355-a98d-3ae7646c4eab",
              "name": "Brown Boots",
              "sku": "PcmProdSku9_837138451097"
            },
            {
              "type": "item",
              "id": "bd098e47-61ea-495e-9f46-653c84c7408e",
              "name": "Yellow Shirt",
              "sku": "PcmProdSku4_837138451062"
            },
            {
              "type": "item",
              "id": "06cd9844-37bc-47d4-945f-290fd034676e",
              "name": "Orange Gloves",
              "sku": "PcmProdSku7_837138451083"
            },
            {
              "type": "item",
              "id": "1a056cb6-4a64-48d2-9aba-be5a4d170676",
              "name": "Green Shoe",
              "sku": "PcmProdSku1_820633028024"
            }
          ]
        }
      }
    },
    {
      "id": "b707614f-00f0-4814-9e6d-211541ed66fb",
      "type": "order",
      "status": "complete",
      "payment": "paid",
      "customer": {
        "name": "Customer 34",
        "email": "customer34@example.com"
      },
      "relationships": {
        "items": {
          "data": [
            {
              "type": "item",
              "id": "874b0cd5-7d20-47c6-a66b-aa5d69be4217",
              "name": "White Socks",
              "sku": "PIMBundle-sku-122527558739"
            },
            {
              "type": "item",
              "id": "9b770b77-61c7-4240-9519-b45764b64d60",
              "name": "Brown Boots",
              "sku": "PcmProdSku9_837138451097"
            },
            {
              "type": "item",
              "id": "2b1a9f1a-73ca-4120-b3d6-8ef86da94046",
              "name": "Purple Scarf",
              "sku": "PcmProdSku6_837138451076"
            },
            {
              "type": "item",
              "id": "5a99a07b-7e14-47a4-9952-e9c786078df8",
              "name": "Red Hat",
              "sku": "PcmProdSku2_837138451048"
            }
          ]
        }
      }
    },
    {
      "id": "156e26d6-615b-4d4a-a55c-1b3018abf1fe",
      "type": "order",
      "status": "complete",
      "payment": "paid",
      "customer": {
        "name": "Customer 35",
        "email": "customer35@example.com"
      },
      "relationships": {
        "items": {
          "data": [
            {
              "type": "item",
              "id": "21c4936e-bdda-403d-a6ba-062350c77aa7",
              "name": "White Socks",
              "sku": "PIMBundle-sku-122527558739"
            },
            {
              "type": "item",
              "id": "e8de1890-dcc9-411a-8ecb-5353dab3917b",
              "name": "Orange Gloves",
              "sku": "PcmProdSku7_837138451083"
            },
            {
              "type": "item",
              "id": "06d2f89c-05a0-4dc7-bd88-d40731d2f0d6",
              "name": "Yellow Shirt",
              "sku": "PcmProdSku4_837138451062"
            },
            {
              "type": "item",
              "id": "be1b0ce7-8ea5-4675-a71e-505e6c39fe6a",
              "name": "Blue Jeans",
              "sku": "PcmProdSku3_837138451055"
            }
          ]
        }
      }
    },
    {
      "id": "9888641d-5184-4508-97b1-319f0d940af7",
      "type": "order",
      "status": "complete",
      "payment": "paid",
      "customer": {
        "name": "Customer 36",
        "email": "customer36@example.com"
      },
      "relationships": {
        "items": {
          "data": [
            {
              "type": "item",
              "id": "c6fe686b-a32c-4a45-b335-09024544db6d",
              "name": "Purple Scarf",
              "sku": "PcmProdSku6_837138451076"
            },
            {
              "type": "item",
              "id": "51c0582e-b463-4d33-8cb5-82bf62aa3e42",
              "name": "White Socks",
              "sku": "PIMBundle-sku-122527558739"
            },
            {
              "type": "item",
              "id": "b040dd7e-be60-48d3-a8b3-7344d765f7f1",
              "name": "Green Shoe",
              "sku": "PcmProdSku1_820633028024"
            }
          ]
        }
      }
    },
    {
      "id": "62ddf317-87b1-465f-8c6c-e938502d8417",
      "type": "order",
      "status": "complete",
      "payment": "paid",
      "customer": {
        "name": "Customer 37",
        "email": "customer37@example.com"
      },
      "relationships": {
        "items": {
          "data": [
            {
              "type": "item",
              "id": "f7ceab57-5019-4208-b238-888358d32e76",
              "name": "Purple Scarf",
              "sku": "PcmProdSku6_837138451076"
            },
            {
              "type": "item",
              "id": "f650e2db-b4e4-40c8-9f53-08472eca8e5a",
              "name": "Black Belt",
              "sku": "PcmProdSku5_837138451069"
            }
          ]
        }
      }
    },
    {
      "id": "c70f6b9b-b788-496a-baf4-f1a89a283d85",
      "type": "order",
      "status": "complete",
      "payment": "paid",
      "customer": {
        "name": "Customer 38",
        "email": "customer38@example.com"
      },
      "relationships": {
        "items": {
          "data": [
            {
              "type": "item",
              "id": "ba941048-8dbf-4775-8fca-b4e4b9fbd909",
              "name": "Pink Hat",
              "sku": "PcmProdSku8_837138451090"
            },
            {
              "type": "item",
              "id": "519ab951-aa7a-4fa2-9e46-df27eba9c656",
              "name": "Yellow Shirt",
              "sku": "PcmProdSku4_837138451062"
            },
            {
              "type": "item",
              "id": "bd8a6493-2252-42f2-8777-b38450048d0a",
              "name": "Red Hat",
              "sku": "PcmProdSku2_837138451048"
            }
          ]
        }
      }
    },
    {
      "id": "79c6de56-caa4-49ba-bf90-c91a4fd2e216",
      "type": "order",
      "status": "complete",
      "payment": "paid",
      "customer": {
        "name": "Customer 39",
        "email": "customer39@example.com"
      },
      "relationships": {
        "items": {
          "data": [
            {
              "type": "item",
              "id": "54c8579a-d1dc-4be6-9dbe-7e28650251f4",
              "name": "Green Shoe",
              "sku": "PcmProdSku1_820633028024"
            },
            {
              "type": "item",
              "id": "3e17e3bd-df6b-4e4a-9d74-9b5e3e282be8",
              "name": "Blue Jeans",
              "sku": "PcmProdSku3_837138451055"
            }
          ]
        }
      }
    },
    {
      "id": "49be6117-bee3-4730-afa2-f3fce63a67cd",
      "type": "order",
      "status": "complete",
      "payment": "paid",
      "customer": {
        "name": "Customer 40",
        "email": "customer40@example.com"
      },
      "relationships": {
        "items": {
          "data": [
            {
              "type": "item",
              "id": "ddc9d13f-1754-4206-bc0e-10c34a9f860c",
              "name": "Red Hat",
              "sku": "PcmProdSku2_837138451048"
            },
            {
              "type": "item",
              "id": "73c6b1c4-2fa1-4ec0-bf88-5ca1414c0297",
              "name": "Purple Scarf",
              "sku": "PcmProdSku6_837138451076"
            },
            {
              "type": "item",
              "id": "d046b4df-4d47-429a-af1c-7c89302b93a2",
              "name": "Blue Jeans",
              "sku": "PcmProdSku3_837138451055"
            }
          ]
        }
      }
    },
    {
      "id": "6038b989-c828-4ee9-8184-c25af42c9f3d",
      "type": "order",
      "status": "complete",
      "payment": "paid",
      "customer": {
        "name": "Customer 41",
        "email": "customer41@example.com"
      },
      "relationships": {
        "items": {
          "data": [
            {
              "type": "item",
              "id": "c57e1ee3-314b-401b-9efb-ba123a1b31a2",
              "name": "Blue Jeans",
              "sku": "PcmProdSku3_837138451055"
            },
            {
              "type": "item",
              "id": "b27cfa28-d9f6-4747-b2a7-f9c36c3b7539",
              "name": "Green Shoe",
              "sku": "PcmProdSku1_820633028024"
            },
            {
              "type": "item",
              "id": "5683d128-32f7-40af-9333-f4f92428bad8",
              "name": "Purple Scarf",
              "sku": "PcmProdSku6_837138451076"
            }
          ]
        }
      }
    },
    {
      "id": "db7b9f41-66cf-43a5-9745-b34ef9d29d54",
      "type": "order",
      "status": "complete",
      "payment": "paid",
      "customer": {
        "name": "Customer 42",
        "email": "customer42@example.com"
      },
      "relationships": {
        "items": {
          "data": [
            {
              "type": "item",
              "id": "5f95ff2f-50b6-4d7e-a39b-1cd88af18a56",
              "name": "Red Hat",
              "sku": "PcmProdSku2_837138451048"
            },
            {
              "type": "item",
              "id": "938ad8e1-787f-44b7-b275-a28787270368",
              "name": "Black Belt",
              "sku": "PcmProdSku5_837138451069"
            },
            {
              "type": "item",
              "id": "bbe2b7a9-ae83-4715-9c2d-d4cd01963801",
              "name": "Purple Scarf",
              "sku": "PcmProdSku6_837138451076"
            }
          ]
        }
      }
    },
    {
      "id": "5aadbf5c-ce91-4e80-9430-ab70464476cd",
      "type": "order",
      "status": "complete",
      "payment": "paid",
      "customer": {
        "name": "Customer 43",
        "email": "customer43@example.com"
      },
      "relationships": {
        "items": {
          "data": [
            {
              "type": "item",
              "id": "8c6fc8cd-9740-4f0e-97a1-47a7dcb90c11",
              "name": "Black Belt",
              "sku": "PcmProdSku5_837138451069"
            },
            {
              "type": "item",
              "id": "87fc3937-4756-4632-9ec4-da6c0a509e7d",
              "name": "Brown Boots",
              "sku": "PcmProdSku9_837138451097"
            },
            {
              "type": "item",
              "id": "5da54663-b52f-4311-a183-09746f8c684a",
              "name": "Green Shoe",
              "sku": "PcmProdSku1_820633028024"
            },
            {
              "type": "item",
              "id": "83a240c7-33c0-4240-8e1c-bb762fa19b1f",
              "name": "Blue Jeans",
              "sku": "PcmProdSku3_837138451055"
            }
          ]
        }
      }
    },
    {
      "id": "48235358-113e-4544-9f3f-3a2f184ee8df",
      "type": "order",
      "status": "complete",
      "payment": "paid",
      "customer": {
        "name": "Customer 44",
        "email": "customer44@example.com"
      },
      "relationships": {
        "items": {
          "data": [
            {
              "type": "item",
              "id": "f89874b4-a52d-468c-80ec-2ab11d11ace1",
              "name": "Yellow Shirt",
              "sku": "PcmProdSku4_837138451062"
            },
            {
              "type": "item",
              "id": "1d181206-77a4-49fa-b615-14b9ce7dd022",
              "name": "Orange Gloves",
              "sku": "PcmProdSku7_837138451083"
            },
            {
              "type": "item",
              "id": "cde77956-0a45-4f46-8d19-3bba0d5788be",
              "name": "White Socks",
              "sku": "PIMBundle-sku-122527558739"
            }
          ]
        }
      }
    },
    {
      "id": "3d87b595-ee20-407f-8781-7ecfd4caed83",
      "type": "order",
      "status": "complete",
      "payment": "paid",
      "customer": {
        "name": "Customer 45",
        "email": "customer45@example.com"
      },
      "relationships": {
        "items": {
          "data": [
            {
              "type": "item",
              "id": "c2aad486-5506-4cbf-b2a9-a7b5a12110a4",
              "name": "Red Hat",
              "sku": "PcmProdSku2_837138451048"
            },
            {
              "type": "item",
              "id": "e2332ce1-d3bf-427f-b52b-156a3c371255",
              "name": "Purple Scarf",
              "sku": "PcmProdSku6_837138451076"
            }
          ]
        }
      }
    },
    {
      "id": "ed8d136e-68dd-4a1a-92c8-57e7980167df",
      "type": "order",
      "status": "complete",
      "payment": "paid",
      "customer": {
        "name": "Customer 46",
        "email": "customer46@example.com"
      },
      "relationships": {
        "items": {
          "data": [
            {
              "type": "item",
              "id": "326be0fb-5eb1-4aa8-8a1b-e7be0650738e",
              "name": "Purple Scarf",
              "sku": "PcmProdSku6_837138451076"
            },
            {
              "type": "item",
              "id": "44f5ab38-cc97-4f6c-bf1a-e41f0899fe52",
              "name": "Red Hat",
              "sku": "PcmProdSku2_837138451048"
            },
            {
              "type": "item",
              "id": "775542ff-a15b-4132-aada-77d2f56bf600",
              "name": "Blue Jeans",
              "sku": "PcmProdSku3_837138451055"
            },
            {
              "type": "item",
              "id": "960c09c2-7ffe-47f4-ad6d-63a51bf3cfc9",
              "name": "Brown Boots",
              "sku": "PcmProdSku9_837138451097"
            }
          ]
        }
      }
    },
    {
      "id": "07db8bda-051f-48a6-9297-82d31728dcc6",
      "type": "order",
      "status": "complete",
      "payment": "paid",
      "customer": {
        "name": "Customer 47",
        "email": "customer47@example.com"
      },
      "relationships": {
        "items": {
          "data": [
            {
              "type": "item",
              "id": "ebaec923-615d-4a43-93a6-dc77ac24aa94",
              "name": "Pink Hat",
              "sku": "PcmProdSku8_837138451090"
            },
            {
              "type": "item",
              "id": "bb5eed35-3aa8-4ae5-a286-710355908c94",
              "name": "Purple Scarf",
              "sku": "PcmProdSku6_837138451076"
            }
          ]
        }
      }
    },
    {
      "id": "806e01ef-8979-431e-bfdf-8ddf5f605fe1",
      "type": "order",
      "status": "complete",
      "payment": "paid",
      "customer": {
        "name": "Customer 48",
        "email": "customer48@example.com"
      },
      "relationships": {
        "items": {
          "data": [
            {
              "type": "item",
              "id": "258dc053-40b4-41aa-a67f-1e768cded7b6",
              "name": "Orange Gloves",
              "sku": "PcmProdSku7_837138451083"
            },
            {
              "type": "item",
              "id": "ad971529-b549-4d85-9e17-f50f662f9c6c",
              "name": "Purple Scarf",
              "sku": "PcmProdSku6_837138451076"
            },
            {
              "type": "item",
              "id": "d5981b93-384e-4741-a0ef-89f9b4ca911d",
              "name": "Black Belt",
              "sku": "PcmProdSku5_837138451069"
            },
            {
              "type": "item",
              "id": "13257d6e-a261-43e0-9151-574673445c0b",
              "name": "Brown Boots",
              "sku": "PcmProdSku9_837138451097"
            }
          ]
        }
      }
    },
    {
      "id": "77c2ce46-3118-4215-a5cd-32662f403f7f",
      "type": "order",
      "status": "complete",
      "payment": "paid",
      "customer": {
        "name": "Customer 49",
        "email": "customer49@example.com"
      },
      "relationships": {
        "items": {
          "data": [
            {
              "type": "item",
              "id": "de66501c-8c55-4eed-8c04-7c16ddbcfc7a",
              "name": "Pink Hat",
              "sku": "PcmProdSku8_837138451090"
            },
            {
              "type": "item",
              "id": "ab14a402-5efa-4f48-b1ea-21429d8dcc60",
              "name": "Green Shoe",
              "sku": "PcmProdSku1_820633028024"
            },
            {
              "type": "item",
              "id": "55bf1945-2446-4b00-8952-b4820bc13f33",
              "name": "Orange Gloves",
              "sku": "PcmProdSku7_837138451083"
            }
          ]
        }
      }
    },
    {
      "id": "dabe1322-0ec7-4750-b147-2cdc21a20a9b",
      "type": "order",
      "status": "complete",
      "payment": "paid",
      "customer": {
        "name": "Customer 50",
        "email": "customer50@example.com"
      },
      "relationships": {
        "items": {
          "data": [
            {
              "type": "item",
              "id": "06b9a750-9bad-462b-82c0-8a612c3b65c3",
              "name": "Purple Scarf",
              "sku": "PcmProdSku6_837138451076"
            },
            {
              "type": "item",
              "id": "3f542da4-cc16-49e8-b86f-0efc7d0d4930",
              "name": "Black Belt",
              "sku": "PcmProdSku5_837138451069"
            },
            {
              "type": "item",
              "id": "0835c2f7-9cb9-44fc-8a29-6e0ece632095",
              "name": "Blue Jeans",
              "sku": "PcmProdSku3_837138451055"
            },
            {
              "type": "item",
              "id": "2b51709c-6c77-46d6-ba1f-68e55145b0c0",
              "name": "Green Shoe",
              "sku": "PcmProdSku1_820633028024"
            }
          ]
        }
      }
    },
    {
      "id": "3f9315c8-6dda-4133-af1f-7eef20c3df45",
      "type": "order",
      "status": "complete",
      "payment": "paid",
      "customer": {
        "name": "Customer 51",
        "email": "customer51@example.com"
      },
      "relationships": {
        "items": {
          "data": [
            {
              "type": "item",
              "id": "af066fa2-b67e-49ff-b073-511673a0c316",
              "name": "Pink Hat",
              "sku": "PcmProdSku8_837138451090"
            },
            {
              "type": "item",
              "id": "3ff970f9-d9aa-45ab-826e-d3ad1e99694e",
              "name": "Black Belt",
              "sku": "PcmProdSku5_837138451069"
            },
            {
              "type": "item",
              "id": "8a2c8d54-1636-4638-b883-0433b122835d",
              "name": "Blue Jeans",
              "sku": "PcmProdSku3_837138451055"
            },
            {
              "type": "item",
              "id": "33a0ea60-ec4f-47f3-9d6b-4006a0d97ca2",
              "name": "Purple Scarf",
              "sku": "PcmProdSku6_837138451076"
            }
          ]
        }
      }
    },
    {
      "id": "d33ffe7f-73d0-4560-a50d-b8193d4176ef",
      "type": "order",
      "status": "complete",
      "payment": "paid",
      "customer": {
        "name": "Customer 52",
        "email": "customer52@example.com"
      },
      "relationships": {
        "items": {
          "data": [
            {
              "type": "item",
              "id": "8a86558f-8748-46cf-8328-bfbe88b03ab2",
              "name": "Purple Scarf",
              "sku": "PcmProdSku6_837138451076"
            },
            {
              "type": "item",
              "id": "188cacef-9fda-45b9-8c38-8dd23a761013",
              "name": "White Socks",
              "sku": "PIMBundle-sku-122527558739"
            },
            {
              "type": "item",
              "id": "2d6b2921-f0c1-44c4-8e0d-1c282b026472",
              "name": "Blue Jeans",
              "sku": "PcmProdSku3_837138451055"
            }
          ]
        }
      }
    },
    {
      "id": "1659c3fd-f808-4523-ad99-d643a6817e1d",
      "type": "order",
      "status": "complete",
      "payment": "paid",
      "customer": {
        "name": "Customer 53",
        "email": "customer53@example.com"
      },
      "relationships": {
        "items": {
          "data": [
            {
              "type": "item",
              "id": "aaa8a155-4bb2-46e9-a409-d15db2247ff2",
              "name": "Brown Boots",
              "sku": "PcmProdSku9_837138451097"
            },
            {
              "type": "item",
              "id": "ce6180ad-45eb-4aa6-99c8-10cd3e2feaa1",
              "name": "White Socks",
              "sku": "PIMBundle-sku-122527558739"
            },
            {
              "type": "item",
              "id": "fd3cc90e-5548-4274-a4c7-420529136808",
              "name": "Red Hat",
              "sku": "PcmProdSku2_837138451048"
            },
            {
              "type": "item",
              "id": "ba2e6473-88ae-44f0-bc3e-5b3bd1d0c50e",
              "name": "Purple Scarf",
              "sku": "PcmProdSku6_837138451076"
            }
          ]
        }
      }
    },
    {
      "id": "ce909b37-18df-4f27-93b5-d11b94647d03",
      "type": "order",
      "status": "complete",
      "payment": "paid",
      "customer": {
        "name": "Customer 54",
        "email": "customer54@example.com"
      },
      "relationships": {
        "items": {
          "data": [
            {
              "type": "item",
              "id": "fa9d3634-ef8a-4795-892e-3451570c6f2c",
              "name": "Yellow Shirt",
              "sku": "PcmProdSku4_837138451062"
            },
            {
              "type": "item",
              "id": "f54c4ede-8828-4690-a803-c8b49a392c40",
              "name": "Blue Jeans",
              "sku": "PcmProdSku3_837138451055"
            }
          ]
        }
      }
    },
    {
      "id": "c68d64d6-5b2e-41c0-8e62-44eb0437c585",
      "type": "order",
      "status": "complete",
      "payment": "paid",
      "customer": {
        "name": "Customer 55",
        "email": "customer55@example.com"
      },
      "relationships": {
        "items": {
          "data": [
            {
              "type": "item",
              "id": "b70dc839-ba56-4fce-a323-7211ec988bca",
              "name": "Orange Gloves",
              "sku": "PcmProdSku7_837138451083"
            },
            {
              "type": "item",
              "id": "fd882898-48ae-471a-8139-da00594de5ff",
              "name": "Red Hat",
              "sku": "PcmProdSku2_837138451048"
            },
            {
              "type": "item",
              "id": "64ffd89d-e32a-416a-8943-797e292a3c83",
              "name": "Yellow Shirt",
              "sku": "PcmProdSku4_837138451062"
            },
            {
              "type": "item",
              "id": "de399ae6-099c-4231-ba4f-bb724c7ece80",
              "name": "Green Shoe",
              "sku": "PcmProdSku1_820633028024"
            }
          ]
        }
      }
    },
    {
      "id": "136b8953-e653-4208-ae97-107e6100b2c7",
      "type": "order",
      "status": "complete",
      "payment": "paid",
      "customer": {
        "name": "Customer 56",
        "email": "customer56@example.com"
      },
      "relationships": {
        "items": {
          "data": [
            {
              "type": "item",
              "id": "9a0ec121-77fb-4fdd-8718-4cbbe758e1b3",
              "name": "White Socks",
              "sku": "PIMBundle-sku-122527558739"
            },
            {
              "type": "item",
              "id": "6bab3bad-131a-4a76-90a3-733982145c88",
              "name": "Red Hat",
              "sku": "PcmProdSku2_837138451048"
            },
            {
              "type": "item",
              "id": "9145f199-0d97-4ac1-a819-421a35e366bc",
              "name": "Brown Boots",
              "sku": "PcmProdSku9_837138451097"
            },
            {
              "type": "item",
              "id": "34fd1774-d5aa-4697-b58f-e6a1aec9337e",
              "name": "Orange Gloves",
              "sku": "PcmProdSku7_837138451083"
            }
          ]
        }
      }
    },
    {
      "id": "75c20c07-9dac-46bf-9698-ce01b3c09a20",
      "type": "order",
      "status": "complete",
      "payment": "paid",
      "customer": {
        "name": "Customer 57",
        "email": "customer57@example.com"
      },
      "relationships": {
        "items": {
          "data": [
            {
              "type": "item",
              "id": "84a3fefc-3125-4411-b367-4e2152277dd9",
              "name": "Orange Gloves",
              "sku": "PcmProdSku7_837138451083"
            },
            {
              "type": "item",
              "id": "9108f62f-06dd-41ab-bdd0-9c36260975e1",
              "name": "Green Shoe",
              "sku": "PcmProdSku1_820633028024"
            },
            {
              "type": "item",
              "id": "447571d5-d79c-4852-8fd7-2654da1d81bf",
              "name": "Red Hat",
              "sku": "PcmProdSku2_837138451048"
            }
          ]
        }
      }
    },
    {
      "id": "7ffb2e69-06b7-410f-8e8b-e29333804299",
      "type": "order",
      "status": "complete",
      "payment": "paid",
      "customer": {
        "name": "Customer 58",
        "email": "customer58@example.com"
      },
      "relationships": {
        "items": {
          "data": [
            {
              "type": "item",
              "id": "1b331566-a214-4fc2-9856-dd21aeba5c22",
              "name": "White Socks",
              "sku": "PIMBundle-sku-122527558739"
            },
            {
              "type": "item",
              "id": "70bcb9f6-78ed-46a7-bd35-9fc66935fb32",
              "name": "Green Shoe",
              "sku": "PcmProdSku1_820633028024"
            }
          ]
        }
      }
    },
    {
      "id": "c664da04-7092-4516-b662-cd1354847b42",
      "type": "order",
      "status": "complete",
      "payment": "paid",
      "customer": {
        "name": "Customer 59",
        "email": "customer59@example.com"
      },
      "relationships": {
        "items": {
          "data": [
            {
              "type": "item",
              "id": "42c322e4-d436-4705-b5b1-59f3c30d275e",
              "name": "Black Belt",
              "sku": "PcmProdSku5_837138451069"
            },
            {
              "type": "item",
              "id": "6874dd03-05f4-4eeb-97fa-6250de8b5345",
              "name": "Blue Jeans",
              "sku": "PcmProdSku3_837138451055"
            },
            {
              "type": "item",
              "id": "60b92628-8bba-47a3-a6c0-965e4a91c647",
              "name": "Pink Hat",
              "sku": "PcmProdSku8_837138451090"
            },
            {
              "type": "item",
              "id": "10039cef-3dfb-4dee-b842-4fb8c1a76892",
              "name": "Red Hat",
              "sku": "PcmProdSku2_837138451048"
            }
          ]
        }
      }
    },
    {
      "id": "0eccd528-2a97-4710-97ad-bba8c3e678f4",
      "type": "order",
      "status": "complete",
      "payment": "paid",
      "customer": {
        "name": "Customer 60",
        "email": "customer60@example.com"
      },
      "relationships": {
        "items": {
          "data": [
            {
              "type": "item",
              "id": "55860dc1-dd41-4a99-bff8-a4992cfb3d5b",
              "name": "Orange Gloves",
              "sku": "PcmProdSku7_837138451083"
            },
            {
              "type": "item",
              "id": "c1129653-dd7b-4ee4-a507-3bc551f1679e",
              "name": "Brown Boots",
              "sku": "PcmProdSku9_837138451097"
            },
            {
              "type": "item",
              "id": "b7994502-153d-4549-a99f-2cf7febc7665",
              "name": "Yellow Shirt",
              "sku": "PcmProdSku4_837138451062"
            }
          ]
        }
      }
    },
    {
      "id": "57cec86c-bbda-4b00-a46c-25bbed156e53",
      "type": "order",
      "status": "complete",
      "payment": "paid",
      "customer": {
        "name": "Customer 61",
        "email": "customer61@example.com"
      },
      "relationships": {
        "items": {
          "data": [
            {
              "type": "item",
              "id": "9f205ed2-8542-419f-acc7-4be2167d9230",
              "name": "Purple Scarf",
              "sku": "PcmProdSku6_837138451076"
            },
            {
              "type": "item",
              "id": "fafad3cd-e558-4ef5-9aeb-2ba97c2511e5",
              "name": "Blue Jeans",
              "sku": "PcmProdSku3_837138451055"
            },
            {
              "type": "item",
              "id": "66dc3952-f479-4a10-aa01-ad76edb23584",
              "name": "Red Hat",
              "sku": "PcmProdSku2_837138451048"
            },
            {
              "type": "item",
              "id": "6deb7557-d4b4-4680-8a75-e3286c903b08",
              "name": "Black Belt",
              "sku": "PcmProdSku5_837138451069"
            }
          ]
        }
      }
    },
    {
      "id": "37d2dbdd-a1f4-4782-9d86-ab32a9f577e7",
      "type": "order",
      "status": "complete",
      "payment": "paid",
      "customer": {
        "name": "Customer 62",
        "email": "customer62@example.com"
      },
      "relationships": {
        "items": {
          "data": [
            {
              "type": "item",
              "id": "70a3cbb9-cf4c-475c-bccc-403cddffc61e",
              "name": "Green Shoe",
              "sku": "PcmProdSku1_820633028024"
            },
            {
              "type": "item",
              "id": "b859290b-38b3-4ecd-b7c6-0e99c2478c3b",
              "name": "Pink Hat",
              "sku": "PcmProdSku8_837138451090"
            },
            {
              "type": "item",
              "id": "8209ab7f-c10f-4c67-afbf-1b769cf3941d",
              "name": "Orange Gloves",
              "sku": "PcmProdSku7_837138451083"
            }
          ]
        }
      }
    },
    {
      "id": "92c25387-1a11-43d8-851a-229029e553ce",
      "type": "order",
      "status": "complete",
      "payment": "paid",
      "customer": {
        "name": "Customer 63",
        "email": "customer63@example.com"
      },
      "relationships": {
        "items": {
          "data": [
            {
              "type": "item",
              "id": "fc401229-16c6-4543-8a20-74fd837e0e01",
              "name": "Yellow Shirt",
              "sku": "PcmProdSku4_837138451062"
            },
            {
              "type": "item",
              "id": "cd39916d-7f4f-4dd4-8e6e-44fdb11c5bc2",
              "name": "Blue Jeans",
              "sku": "PcmProdSku3_837138451055"
            },
            {
              "type": "item",
              "id": "397eae17-5cab-4e09-adf7-e0cb86d65121",
              "name": "White Socks",
              "sku": "PIMBundle-sku-122527558739"
            }
          ]
        }
      }
    },
    {
      "id": "02807c70-b641-4a84-b9b3-dd461ac46756",
      "type": "order",
      "status": "complete",
      "payment": "paid",
      "customer": {
        "name": "Customer 64",
        "email": "customer64@example.com"
      },
      "relationships": {
        "items": {
          "data": [
            {
              "type": "item",
              "id": "97f53ef7-721e-424d-9e11-123295f88e17",
              "name": "Pink Hat",
              "sku": "PcmProdSku8_837138451090"
            },
            {
              "type": "item",
              "id": "9ac32ba4-785d-435d-8055-78970791ac4b",
              "name": "Blue Jeans",
              "sku": "PcmProdSku3_837138451055"
            },
            {
              "type": "item",
              "id": "9429b9a5-b3c1-4cb3-bec0-86cd1ac3abc1",
              "name": "Green Shoe",
              "sku": "PcmProdSku1_820633028024"
            }
          ]
        }
      }
    },
    {
      "id": "9de5b708-cb19-4349-aa33-1eaa1b3a8459",
      "type": "order",
      "status": "complete",
      "payment": "paid",
      "customer": {
        "name": "Customer 65",
        "email": "customer65@example.com"
      },
      "relationships": {
        "items": {
          "data": [
            {
              "type": "item",
              "id": "32755fdc-b261-436f-b56d-b33c664fab9c",
              "name": "Pink Hat",
              "sku": "PcmProdSku8_837138451090"
            },
            {
              "type": "item",
              "id": "86bdbf50-5423-4f18-b949-25186ce236ca",
              "name": "Green Shoe",
              "sku": "PcmProdSku1_820633028024"
            },
            {
              "type": "item",
              "id": "f7c0ac80-593d-48b3-8d14-c614ccf55444",
              "name": "White Socks",
              "sku": "PIMBundle-sku-122527558739"
            }
          ]
        }
      }
    },
    {
      "id": "29d3e0d2-ee26-44f0-943a-d4e6fd52fcfe",
      "type": "order",
      "status": "complete",
      "payment": "paid",
      "customer": {
        "name": "Customer 66",
        "email": "customer66@example.com"
      },
      "relationships": {
        "items": {
          "data": [
            {
              "type": "item",
              "id": "ad6bde9b-e0f4-4c2e-8a4b-353560a33ccc",
              "name": "Green Shoe",
              "sku": "PcmProdSku1_820633028024"
            },
            {
              "type": "item",
              "id": "30e1ad64-abad-4f97-a924-4af71495d34b",
              "name": "Brown Boots",
              "sku": "PcmProdSku9_837138451097"
            },
            {
              "type": "item",
              "id": "6255d6a3-c346-4c14-b6a7-f20cb4949464",
              "name": "Blue Jeans",
              "sku": "PcmProdSku3_837138451055"
            }
          ]
        }
      }
    },
    {
      "id": "d14c7628-6b91-431b-91c1-4b7025a96952",
      "type": "order",
      "status": "complete",
      "payment": "paid",
      "customer": {
        "name": "Customer 67",
        "email": "customer67@example.com"
      },
      "relationships": {
        "items": {
          "data": [
            {
              "type": "item",
              "id": "37fb6ac1-9d4b-4b7b-9b6b-18a67815e3aa",
              "name": "Red Hat",
              "sku": "PcmProdSku2_837138451048"
            },
            {
              "type": "item",
              "id": "413cf068-c360-4030-a8f9-474cd01585fb",
              "name": "Orange Gloves",
              "sku": "PcmProdSku7_837138451083"
            },
            {
              "type": "item",
              "id": "235d1d5e-2b91-4a0c-a198-cb75f6417768",
              "name": "Black Belt",
              "sku": "PcmProdSku5_837138451069"
            }
          ]
        }
      }
    },
    {
      "id": "45964c49-2f66-4fd2-b3dd-7ede551e6dbe",
      "type": "order",
      "status": "complete",
      "payment": "paid",
      "customer": {
        "name": "Customer 68",
        "email": "customer68@example.com"
      },
      "relationships": {
        "items": {
          "data": [
            {
              "type": "item",
              "id": "c687b299-881c-4078-9196-196d510027fb",
              "name": "Blue Jeans",
              "sku": "PcmProdSku3_837138451055"
            },
            {
              "type": "item",
              "id": "d0a9a0a6-6bf0-4bc3-aaba-ffb9acb5d9a9",
              "name": "Yellow Shirt",
              "sku": "PcmProdSku4_837138451062"
            },
            {
              "type": "item",
              "id": "f0235093-ceb6-4036-aec7-291756124509",
              "name": "Green Shoe",
              "sku": "PcmProdSku1_820633028024"
            },
            {
              "type": "item",
              "id": "d6ccd9aa-2f43-4fef-be21-8f8e087e3b38",
              "name": "Orange Gloves",
              "sku": "PcmProdSku7_837138451083"
            }
          ]
        }
      }
    },
    {
      "id": "751853df-37ed-4ed7-9240-e1e0dee96f41",
      "type": "order",
      "status": "complete",
      "payment": "paid",
      "customer": {
        "name": "Customer 69",
        "email": "customer69@example.com"
      },
      "relationships": {
        "items": {
          "data": [
            {
              "type": "item",
              "id": "cb560c72-e8b7-466e-acff-2844a5340c57",
              "name": "Orange Gloves",
              "sku": "PcmProdSku7_837138451083"
            },
            {
              "type": "item",
              "id": "018a6fa5-39e0-4bc3-b170-8d5e530afca2",
              "name": "Green Shoe",
              "sku": "PcmProdSku1_820633028024"
            }
          ]
        }
      }
    },
    {
      "id": "0605392a-0b3e-48c5-aff5-dd9a01d52ed7",
      "type": "order",
      "status": "complete",
      "payment": "paid",
      "customer": {
        "name": "Customer 70",
        "email": "customer70@example.com"
      },
      "relationships": {
        "items": {
          "data": [
            {
              "type": "item",
              "id": "ba0fe891-9ddb-4b74-be1c-e6a094e209bc",
              "name": "Yellow Shirt",
              "sku": "PcmProdSku4_837138451062"
            },
            {
              "type": "item",
              "id": "dcbcad94-8275-42cd-9598-08de47337e0b",
              "name": "Red Hat",
              "sku": "PcmProdSku2_837138451048"
            },
            {
              "type": "item",
              "id": "e7a715b5-c9d0-42e7-ae5a-cafd2e487053",
              "name": "Brown Boots",
              "sku": "PcmProdSku9_837138451097"
            },
            {
              "type": "item",
              "id": "9f2745d3-5df1-450e-8c9e-c1746ada7ed1",
              "name": "Blue Jeans",
              "sku": "PcmProdSku3_837138451055"
            }
          ]
        }
      }
    },
    {
      "id": "9fdd283b-8ed8-49a7-819d-d7e7c7f9d08a",
      "type": "order",
      "status": "complete",
      "payment": "paid",
      "customer": {
        "name": "Customer 71",
        "email": "customer71@example.com"
      },
      "relationships": {
        "items": {
          "data": [
            {
              "type": "item",
              "id": "1ef9f23a-0aa5-40b4-a8ee-e48271e07975",
              "name": "White Socks",
              "sku": "PIMBundle-sku-122527558739"
            },
            {
              "type": "item",
              "id": "f03b4596-3d86-451f-9706-e124146bcbf4",
              "name": "Blue Jeans",
              "sku": "PcmProdSku3_837138451055"
            }
          ]
        }
      }
    },
    {
      "id": "2e17635a-daf2-45ef-995e-e376673f47ff",
      "type": "order",
      "status": "complete",
      "payment": "paid",
      "customer": {
        "name": "Customer 72",
        "email": "customer72@example.com"
      },
      "relationships": {
        "items": {
          "data": [
            {
              "type": "item",
              "id": "e3a64987-3a90-4382-9688-d9e1dc782fca",
              "name": "Red Hat",
              "sku": "PcmProdSku2_837138451048"
            },
            {
              "type": "item",
              "id": "d281d1f7-74e6-431a-8d70-b9b07a7b29e8",
              "name": "Pink Hat",
              "sku": "PcmProdSku8_837138451090"
            },
            {
              "type": "item",
              "id": "17bdb5fe-f5e7-4bee-aa63-fc7bf2ce8255",
              "name": "Black Belt",
              "sku": "PcmProdSku5_837138451069"
            }
          ]
        }
      }
    },
    {
      "id": "a9e1fc58-8721-4274-a9f6-32b978c4dbe7",
      "type": "order",
      "status": "complete",
      "payment": "paid",
      "customer": {
        "name": "Customer 73",
        "email": "customer73@example.com"
      },
      "relationships": {
        "items": {
          "data": [
            {
              "type": "item",
              "id": "c9db20e3-800b-4c91-b136-1d5286e536a3",
              "name": "White Socks",
              "sku": "PIMBundle-sku-122527558739"
            },
            {
              "type": "item",
              "id": "56b0acb0-3fa9-4f50-b2c0-0a9b12471356",
              "name": "Brown Boots",
              "sku": "PcmProdSku9_837138451097"
            }
          ]
        }
      }
    },
    {
      "id": "66fff01e-56b3-4de5-b01b-0b5d47ff613d",
      "type": "order",
      "status": "complete",
      "payment": "paid",
      "customer": {
        "name": "Customer 74",
        "email": "customer74@example.com"
      },
      "relationships": {
        "items": {
          "data": [
            {
              "type": "item",
              "id": "f70174f6-5186-4a56-94a5-06074f5ccb6b",
              "name": "Blue Jeans",
              "sku": "PcmProdSku3_837138451055"
            },
            {
              "type": "item",
              "id": "1ee59e2d-ea3b-4562-8772-11626943825b",
              "name": "Orange Gloves",
              "sku": "PcmProdSku7_837138451083"
            },
            {
              "type": "item",
              "id": "ac2fc0ee-54ae-4e97-bbc0-432794aa1994",
              "name": "Green Shoe",
              "sku": "PcmProdSku1_820633028024"
            }
          ]
        }
      }
    },
    {
      "id": "755795b3-f1fb-487a-8b58-e61750a31fd2",
      "type": "order",
      "status": "complete",
      "payment": "paid",
      "customer": {
        "name": "Customer 75",
        "email": "customer75@example.com"
      },
      "relationships": {
        "items": {
          "data": [
            {
              "type": "item",
              "id": "4b3f0dd1-1cd5-4d58-af33-9adce5a94d9b",
              "name": "Yellow Shirt",
              "sku": "PcmProdSku4_837138451062"
            },
            {
              "type": "item",
              "id": "75770076-6415-4216-88b9-0e9318dd69b1",
              "name": "Purple Scarf",
              "sku": "PcmProdSku6_837138451076"
            }
          ]
        }
      }
    },
    {
      "id": "cc746c90-6695-4026-b727-9371f04028af",
      "type": "order",
      "status": "complete",
      "payment": "paid",
      "customer": {
        "name": "Customer 76",
        "email": "customer76@example.com"
      },
      "relationships": {
        "items": {
          "data": [
            {
              "type": "item",
              "id": "14ec5f64-b487-4903-bd63-198ababd8ea9",
              "name": "Brown Boots",
              "sku": "PcmProdSku9_837138451097"
            },
            {
              "type": "item",
              "id": "30d589bf-8294-4d7d-bd13-b033fe3a35f3",
              "name": "Pink Hat",
              "sku": "PcmProdSku8_837138451090"
            }
          ]
        }
      }
    },
    {
      "id": "90c705b9-fdd9-4e89-8d82-645d09e197fb",
      "type": "order",
      "status": "complete",
      "payment": "paid",
      "customer": {
        "name": "Customer 77",
        "email": "customer77@example.com"
      },
      "relationships": {
        "items": {
          "data": [
            {
              "type": "item",
              "id": "38fbc6ac-37e0-4c95-95db-3767c525bb22",
              "name": "Black Belt",
              "sku": "PcmProdSku5_837138451069"
            },
            {
              "type": "item",
              "id": "030b5429-6f69-4106-adca-fc1374f821e0",
              "name": "Brown Boots",
              "sku": "PcmProdSku9_837138451097"
            },
            {
              "type": "item",
              "id": "e038b0d8-9503-4e6f-8a08-1c1e9d20bd45",
              "name": "Orange Gloves",
              "sku": "PcmProdSku7_837138451083"
            },
            {
              "type": "item",
              "id": "5f48e5ab-0f03-4140-b667-4bc4ccd6ef04",
              "name": "White Socks",
              "sku": "PIMBundle-sku-122527558739"
            }
          ]
        }
      }
    },
    {
      "id": "54fcda8d-8ea1-4945-bb5d-1d2000334160",
      "type": "order",
      "status": "complete",
      "payment": "paid",
      "customer": {
        "name": "Customer 78",
        "email": "customer78@example.com"
      },
      "relationships": {
        "items": {
          "data": [
            {
              "type": "item",
              "id": "13d466df-33f0-46f7-bc0a-34f5a233b079",
              "name": "Pink Hat",
              "sku": "PcmProdSku8_837138451090"
            },
            {
              "type": "item",
              "id": "23b9d52c-f6c4-4f84-8c61-33832c71484a",
              "name": "Red Hat",
              "sku": "PcmProdSku2_837138451048"
            }
          ]
        }
      }
    },
    {
      "id": "c95436f4-75f6-4914-886d-b9f727ba20b7",
      "type": "order",
      "status": "complete",
      "payment": "paid",
      "customer": {
        "name": "Customer 79",
        "email": "customer79@example.com"
      },
      "relationships": {
        "items": {
          "data": [
            {
              "type": "item",
              "id": "47d9416a-1112-40d3-b068-b6d9ae69bcb0",
              "name": "Red Hat",
              "sku": "PcmProdSku2_837138451048"
            },
            {
              "type": "item",
              "id": "a1a14677-3118-4355-8053-9abae1fa779d",
              "name": "Pink Hat",
              "sku": "PcmProdSku8_837138451090"
            }
          ]
        }
      }
    },
    {
      "id": "9e2c0c05-4d95-465e-92b0-6c0b38b0f471",
      "type": "order",
      "status": "complete",
      "payment": "paid",
      "customer": {
        "name": "Customer 80",
        "email": "customer80@example.com"
      },
      "relationships": {
        "items": {
          "data": [
            {
              "type": "item",
              "id": "4d126c71-d3a6-4139-a822-6c73c934a669",
              "name": "Green Shoe",
              "sku": "PcmProdSku1_820633028024"
            },
            {
              "type": "item",
              "id": "75fc59bd-e0c1-4e6b-8256-5d073f2a58f5",
              "name": "Blue Jeans",
              "sku": "PcmProdSku3_837138451055"
            },
            {
              "type": "item",
              "id": "3e315881-81a1-4088-8a8a-e69a5566dbfc",
              "name": "White Socks",
              "sku": "PIMBundle-sku-122527558739"
            },
            {
              "type": "item",
              "id": "dc4a1608-edc9-4989-be75-150362ac80b1",
              "name": "Yellow Shirt",
              "sku": "PcmProdSku4_837138451062"
            }
          ]
        }
      }
    },
    {
      "id": "7b0f474b-9039-43c0-8bc0-c1e190931973",
      "type": "order",
      "status": "complete",
      "payment": "paid",
      "customer": {
        "name": "Customer 81",
        "email": "customer81@example.com"
      },
      "relationships": {
        "items": {
          "data": [
            {
              "type": "item",
              "id": "b9cb0a7c-6e4e-45d4-8840-7bf1a65982ed",
              "name": "Brown Boots",
              "sku": "PcmProdSku9_837138451097"
            },
            {
              "type": "item",
              "id": "da4b3286-2c9e-4d3f-b839-72925df710aa",
              "name": "Red Hat",
              "sku": "PcmProdSku2_837138451048"
            }
          ]
        }
      }
    },
    {
      "id": "6effbd7d-07e7-4848-9cd2-29a08e25b777",
      "type": "order",
      "status": "complete",
      "payment": "paid",
      "customer": {
        "name": "Customer 82",
        "email": "customer82@example.com"
      },
      "relationships": {
        "items": {
          "data": [
            {
              "type": "item",
              "id": "794b8236-b061-4293-a214-09415610f2b9",
              "name": "Yellow Shirt",
              "sku": "PcmProdSku4_837138451062"
            },
            {
              "type": "item",
              "id": "68aac696-91cd-4d7b-a903-64b74b3e829e",
              "name": "Purple Scarf",
              "sku": "PcmProdSku6_837138451076"
            }
          ]
        }
      }
    },
    {
      "id": "ae49306d-99c6-4669-af63-21cd42cd8018",
      "type": "order",
      "status": "complete",
      "payment": "paid",
      "customer": {
        "name": "Customer 83",
        "email": "customer83@example.com"
      },
      "relationships": {
        "items": {
          "data": [
            {
              "type": "item",
              "id": "b7afd6cd-9c58-4c4b-bc77-fcdf45347d81",
              "name": "Yellow Shirt",
              "sku": "PcmProdSku4_837138451062"
            },
            {
              "type": "item",
              "id": "3cf5ea94-58b1-4a53-9fcb-149d56784223",
              "name": "Pink Hat",
              "sku": "PcmProdSku8_837138451090"
            },
            {
              "type": "item",
              "id": "2c8062e9-5792-4106-8ee9-ae832d9ce92b",
              "name": "Red Hat",
              "sku": "PcmProdSku2_837138451048"
            }
          ]
        }
      }
    },
    {
      "id": "204fa698-cfd6-4054-8009-291b97a6cfb5",
      "type": "order",
      "status": "complete",
      "payment": "paid",
      "customer": {
        "name": "Customer 84",
        "email": "customer84@example.com"
      },
      "relationships": {
        "items": {
          "data": [
            {
              "type": "item",
              "id": "56fdd797-b724-4dd8-82d4-985005a2a02b",
              "name": "Pink Hat",
              "sku": "PcmProdSku8_837138451090"
            },
            {
              "type": "item",
              "id": "ed5ed27e-6a82-410d-8662-3198865cfa2a",
              "name": "Orange Gloves",
              "sku": "PcmProdSku7_837138451083"
            },
            {
              "type": "item",
              "id": "34e7568f-6a3e-4707-8abc-678d4fa3d95b",
              "name": "Blue Jeans",
              "sku": "PcmProdSku3_837138451055"
            },
            {
              "type": "item",
              "id": "9835c0f9-d177-4533-b86f-c265dfb088bb",
              "name": "Green Shoe",
              "sku": "PcmProdSku1_820633028024"
            }
          ]
        }
      }
    },
    {
      "id": "edb36b3b-2908-42bc-9085-8ad2a951f30e",
      "type": "order",
      "status": "complete",
      "payment": "paid",
      "customer": {
        "name": "Customer 85",
        "email": "customer85@example.com"
      },
      "relationships": {
        "items": {
          "data": [
            {
              "type": "item",
              "id": "8afaabf5-ead4-4621-b423-f39a042b3ba5",
              "name": "Green Shoe",
              "sku": "PcmProdSku1_820633028024"
            },
            {
              "type": "item",
              "id": "3c0546e9-c25d-43c5-8c90-3d74298fd112",
              "name": "Pink Hat",
              "sku": "PcmProdSku8_837138451090"
            },
            {
              "type": "item",
              "id": "994a2eff-cbcc-45ae-96ac-12da2b09184c",
              "name": "Black Belt",
              "sku": "PcmProdSku5_837138451069"
            },
            {
              "type": "item",
              "id": "79daf858-0868-4afc-8bd2-b9542c7c8060",
              "name": "Purple Scarf",
              "sku": "PcmProdSku6_837138451076"
            }
          ]
        }
      }
    },
    {
      "id": "b7d5b02b-47fb-4ee2-8f07-3b6c60d3ce03",
      "type": "order",
      "status": "complete",
      "payment": "paid",
      "customer": {
        "name": "Customer 86",
        "email": "customer86@example.com"
      },
      "relationships": {
        "items": {
          "data": [
            {
              "type": "item",
              "id": "28c13e07-e030-47c4-9860-a34a79b8596a",
              "name": "Red Hat",
              "sku": "PcmProdSku2_837138451048"
            },
            {
              "type": "item",
              "id": "97b3cf41-b247-4909-8af6-8b3552ab83da",
              "name": "Purple Scarf",
              "sku": "PcmProdSku6_837138451076"
            },
            {
              "type": "item",
              "id": "cb079a9a-5571-4494-829d-6b6e23a96aa9",
              "name": "Brown Boots",
              "sku": "PcmProdSku9_837138451097"
            },
            {
              "type": "item",
              "id": "c6ce9a12-f0a0-4650-8926-a1137e518464",
              "name": "Blue Jeans",
              "sku": "PcmProdSku3_837138451055"
            }
          ]
        }
      }
    },
    {
      "id": "fb78ccf4-cac2-40ed-a3fb-9639952c9d9b",
      "type": "order",
      "status": "complete",
      "payment": "paid",
      "customer": {
        "name": "Customer 87",
        "email": "customer87@example.com"
      },
      "relationships": {
        "items": {
          "data": [
            {
              "type": "item",
              "id": "adda15fb-ac7d-4500-b312-fc672da2d524",
              "name": "White Socks",
              "sku": "PIMBundle-sku-122527558739"
            },
            {
              "type": "item",
              "id": "b958d19f-958a-4fc4-a2bc-6afa4246dc6d",
              "name": "Brown Boots",
              "sku": "PcmProdSku9_837138451097"
            },
            {
              "type": "item",
              "id": "f4b78964-5dad-4f7e-8950-92f2933aac9f",
              "name": "Blue Jeans",
              "sku": "PcmProdSku3_837138451055"
            },
            {
              "type": "item",
              "id": "2b0b9079-a976-4485-ae77-7c01ffbd820f",
              "name": "Black Belt",
              "sku": "PcmProdSku5_837138451069"
            }
          ]
        }
      }
    },
    {
      "id": "e5f8f0db-831e-4465-a798-003f9330c0c2",
      "type": "order",
      "status": "complete",
      "payment": "paid",
      "customer": {
        "name": "Customer 88",
        "email": "customer88@example.com"
      },
      "relationships": {
        "items": {
          "data": [
            {
              "type": "item",
              "id": "80491b6a-cb2a-4327-8e16-72e6394181b0",
              "name": "Brown Boots",
              "sku": "PcmProdSku9_837138451097"
            },
            {
              "type": "item",
              "id": "c291e42b-1a88-4ead-b81b-79ec41be73dd",
              "name": "Purple Scarf",
              "sku": "PcmProdSku6_837138451076"
            },
            {
              "type": "item",
              "id": "c958dd28-2b2b-4044-8af7-e4adec4b80fb",
              "name": "Yellow Shirt",
              "sku": "PcmProdSku4_837138451062"
            },
            {
              "type": "item",
              "id": "901d9650-5805-4617-85cb-959e617fbd4c",
              "name": "Red Hat",
              "sku": "PcmProdSku2_837138451048"
            }
          ]
        }
      }
    },
    {
      "id": "35dd7f5a-08db-4449-b09c-2064d93fed88",
      "type": "order",
      "status": "complete",
      "payment": "paid",
      "customer": {
        "name": "Customer 89",
        "email": "customer89@example.com"
      },
      "relationships": {
        "items": {
          "data": [
            {
              "type": "item",
              "id": "d2e57908-9d9a-4416-b0b1-97b71a1fc08d",
              "name": "Purple Scarf",
              "sku": "PcmProdSku6_837138451076"
            },
            {
              "type": "item",
              "id": "912f5954-406e-42f9-a0ec-9849160fe1cb",
              "name": "Yellow Shirt",
              "sku": "PcmProdSku4_837138451062"
            },
            {
              "type": "item",
              "id": "60a765b4-db16-43c3-a011-d645cafc856c",
              "name": "Pink Hat",
              "sku": "PcmProdSku8_837138451090"
            }
          ]
        }
      }
    },
    {
      "id": "6e04abd5-16aa-4c93-a999-d2f93b46a4db",
      "type": "order",
      "status": "complete",
      "payment": "paid",
      "customer": {
        "name": "Customer 90",
        "email": "customer90@example.com"
      },
      "relationships": {
        "items": {
          "data": [
            {
              "type": "item",
              "id": "709040b6-3c56-4151-8710-d30c4e879775",
              "name": "Black Belt",
              "sku": "PcmProdSku5_837138451069"
            },
            {
              "type": "item",
              "id": "dea5a34b-e657-4679-8a23-c14ce7533f1b",
              "name": "Orange Gloves",
              "sku": "PcmProdSku7_837138451083"
            },
            {
              "type": "item",
              "id": "9cf22053-a270-49f9-b858-d054194ab73c",
              "name": "Green Shoe",
              "sku": "PcmProdSku1_820633028024"
            },
            {
              "type": "item",
              "id": "f7c87206-c502-415c-a300-16e06891b554",
              "name": "Yellow Shirt",
              "sku": "PcmProdSku4_837138451062"
            }
          ]
        }
      }
    },
    {
      "id": "1276436a-26f9-4b62-910e-2d9f4d10cbfa",
      "type": "order",
      "status": "complete",
      "payment": "paid",
      "customer": {
        "name": "Customer 91",
        "email": "customer91@example.com"
      },
      "relationships": {
        "items": {
          "data": [
            {
              "type": "item",
              "id": "7d72e1c2-438b-4a1b-a79f-bad389da2a38",
              "name": "White Socks",
              "sku": "PIMBundle-sku-122527558739"
            },
            {
              "type": "item",
              "id": "fadccec5-2188-4fc5-9202-7fe279e3d073",
              "name": "Brown Boots",
              "sku": "PcmProdSku9_837138451097"
            }
          ]
        }
      }
    },
    {
      "id": "f717583d-51e0-45a8-a9bb-e809612d8f83",
      "type": "order",
      "status": "complete",
      "payment": "paid",
      "customer": {
        "name": "Customer 92",
        "email": "customer92@example.com"
      },
      "relationships": {
        "items": {
          "data": [
            {
              "type": "item",
              "id": "68a3d4df-be75-4699-bd85-8b9069a1d77c",
              "name": "Purple Scarf",
              "sku": "PcmProdSku6_837138451076"
            },
            {
              "type": "item",
              "id": "d2247d30-d66b-4d3d-b481-16d7e251999d",
              "name": "Black Belt",
              "sku": "PcmProdSku5_837138451069"
            },
            {
              "type": "item",
              "id": "97d6a292-b812-47c0-b108-d52bc7791a27",
              "name": "Yellow Shirt",
              "sku": "PcmProdSku4_837138451062"
            },
            {
              "type": "item",
              "id": "a42ec101-3ef3-4f3f-88ad-9b1a5d32432f",
              "name": "White Socks",
              "sku": "PIMBundle-sku-122527558739"
            }
          ]
        }
      }
    },
    {
      "id": "8aeb7a5a-ce60-4c1f-801b-7897abe0e8eb",
      "type": "order",
      "status": "complete",
      "payment": "paid",
      "customer": {
        "name": "Customer 93",
        "email": "customer93@example.com"
      },
      "relationships": {
        "items": {
          "data": [
            {
              "type": "item",
              "id": "8fc3d777-6a37-4448-8060-e9d943134170",
              "name": "Red Hat",
              "sku": "PcmProdSku2_837138451048"
            },
            {
              "type": "item",
              "id": "e03d2605-bdc2-41b4-8766-e8cfb0bb4c81",
              "name": "Blue Jeans",
              "sku": "PcmProdSku3_837138451055"
            },
            {
              "type": "item",
              "id": "b9e060f7-5f78-430b-9847-7e61a54e8bb0",
              "name": "Orange Gloves",
              "sku": "PcmProdSku7_837138451083"
            },
            {
              "type": "item",
              "id": "b06dde35-0e63-4ec6-9ead-fe405e3940d1",
              "name": "White Socks",
              "sku": "PIMBundle-sku-122527558739"
            }
          ]
        }
      }
    },
    {
      "id": "38be7fb1-c1cc-48a0-acd4-2e5e648b2935",
      "type": "order",
      "status": "complete",
      "payment": "paid",
      "customer": {
        "name": "Customer 94",
        "email": "customer94@example.com"
      },
      "relationships": {
        "items": {
          "data": [
            {
              "type": "item",
              "id": "6f108dac-4aff-4663-ac5f-a61e07a60e0a",
              "name": "Red Hat",
              "sku": "PcmProdSku2_837138451048"
            },
            {
              "type": "item",
              "id": "8b6688d0-87c0-4f4c-823e-789d191952b6",
              "name": "Green Shoe",
              "sku": "PcmProdSku1_820633028024"
            }
          ]
        }
      }
    },
    {
      "id": "d7345c4e-d99d-4c19-a461-338c098dad6e",
      "type": "order",
      "status": "complete",
      "payment": "paid",
      "customer": {
        "name": "Customer 95",
        "email": "customer95@example.com"
      },
      "relationships": {
        "items": {
          "data": [
            {
              "type": "item",
              "id": "4f4511d1-bfca-4c7e-8222-9fb7887c497c",
              "name": "Yellow Shirt",
              "sku": "PcmProdSku4_837138451062"
            },
            {
              "type": "item",
              "id": "1ab6ff33-c017-4da2-be69-81fa45a6cc4d",
              "name": "Orange Gloves",
              "sku": "PcmProdSku7_837138451083"
            }
          ]
        }
      }
    },
    {
      "id": "09f55317-9978-4261-ba91-86c005104f54",
      "type": "order",
      "status": "complete",
      "payment": "paid",
      "customer": {
        "name": "Customer 96",
        "email": "customer96@example.com"
      },
      "relationships": {
        "items": {
          "data": [
            {
              "type": "item",
              "id": "803e322a-d667-4151-8110-0b94b449480e",
              "name": "Blue Jeans",
              "sku": "PcmProdSku3_837138451055"
            },
            {
              "type": "item",
              "id": "07bd7869-a1f7-47c9-962b-435de7e56b07",
              "name": "Black Belt",
              "sku": "PcmProdSku5_837138451069"
            }
          ]
        }
      }
    },
    {
      "id": "c3e7b424-bafa-4e95-af51-d2b898083fd5",
      "type": "order",
      "status": "complete",
      "payment": "paid",
      "customer": {
        "name": "Customer 97",
        "email": "customer97@example.com"
      },
      "relationships": {
        "items": {
          "data": [
            {
              "type": "item",
              "id": "ba5538b1-c240-42bd-8a33-3f18f685183a",
              "name": "Pink Hat",
              "sku": "PcmProdSku8_837138451090"
            },
            {
              "type": "item",
              "id": "934580c6-5373-4cd6-be22-5f2ab8e1eec5",
              "name": "Purple Scarf",
              "sku": "PcmProdSku6_837138451076"
            },
            {
              "type": "item",
              "id": "2e49570d-840f-4459-832e-eda728236484",
              "name": "Yellow Shirt",
              "sku": "PcmProdSku4_837138451062"
            }
          ]
        }
      }
    },
    {
      "id": "626c0376-9bde-4940-ace0-8aa888dab141",
      "type": "order",
      "status": "complete",
      "payment": "paid",
      "customer": {
        "name": "Customer 98",
        "email": "customer98@example.com"
      },
      "relationships": {
        "items": {
          "data": [
            {
              "type": "item",
              "id": "d5963939-f8c9-4027-a122-a9716be474d9",
              "name": "Red Hat",
              "sku": "PcmProdSku2_837138451048"
            },
            {
              "type": "item",
              "id": "7cd1ccb3-a8ba-4bdb-a374-ba3fbfaa00b8",
              "name": "Purple Scarf",
              "sku": "PcmProdSku6_837138451076"
            },
            {
              "type": "item",
              "id": "f1d2ef47-4928-4367-b26f-5c94786100be",
              "name": "Green Shoe",
              "sku": "PcmProdSku1_820633028024"
            },
            {
              "type": "item",
              "id": "3b90c4a7-f551-4b04-a861-9db50fd8a38e",
              "name": "Blue Jeans",
              "sku": "PcmProdSku3_837138451055"
            }
          ]
        }
      }
    },
    {
      "id": "1d9e64a1-a5a7-45aa-9bfa-d09d12185b2c",
      "type": "order",
      "status": "complete",
      "payment": "paid",
      "customer": {
        "name": "Customer 99",
        "email": "customer99@example.com"
      },
      "relationships": {
        "items": {
          "data": [
            {
              "type": "item",
              "id": "fc34a9f0-e69c-4aad-a20a-a22a7827e691",
              "name": "Brown Boots",
              "sku": "PcmProdSku9_837138451097"
            },
            {
              "type": "item",
              "id": "6621f841-489b-45c3-ae7e-fea94a5c33b5",
              "name": "White Socks",
              "sku": "PIMBundle-sku-122527558739"
            }
          ]
        }
      }
    },
    {
      "id": "91d4eea3-ba19-4d12-b5e4-5f957f40074c",
      "type": "order",
      "status": "complete",
      "payment": "paid",
      "customer": {
        "name": "Customer 100",
        "email": "customer100@example.com"
      },
      "relationships": {
        "items": {
          "data": [
            {
              "type": "item",
              "id": "238b1495-7373-49a7-9c6c-6e4491c99141",
              "name": "Green Shoe",
              "sku": "PcmProdSku1_820633028024"
            },
            {
              "type": "item",
              "id": "4f34c4c3-f3f9-4e7f-be8d-04b39f689ed2",
              "name": "Yellow Shirt",
              "sku": "PcmProdSku4_837138451062"
            },
            {
              "type": "item",
              "id": "d0c15167-3f25-40b1-8f1b-29bafd744130",
              "name": "Blue Jeans",
              "sku": "PcmProdSku3_837138451055"
            },
            {
              "type": "item",
              "id": "9900a3c2-bab6-4135-b2a5-2bb4b3fba44f",
              "name": "White Socks",
              "sku": "PIMBundle-sku-122527558739"
            }
          ]
        }
      }
    }
  ]
}